tkst.py
tkst-0.1.2.dist-info/LICENSE
tkst-0.1.2.dist-info/METADATA
tkst-0.1.2.dist-info/WHEEL
tkst-0.1.2.dist-info/top_level.txt
tkst-0.1.2.dist-info/RECORD
