Metadata-Version: 2.1
Name: tkst
Version: 0.1.2
Summary: preview projects using the ST7789 display in a tkinter window
Home-page: https://github.com/mmmsoup/tkst
Author: mmmsoup
Author-email: mmmsoup@protonmail.com
License: MIT
Platform: UNKNOWN
Classifier: Programming Language :: Python :: 3
Requires-Python: >=3.6
Requires-Dist: Pillow
